{
  "pipeline": "short",
  "train_window": [
    "2025-07-13 13:00:00",
    "2025-07-28 13:00:00"
  ],
  "oos_window": [
    "2025-07-28 13:00:00",
    "2025-08-05 13:00:00"
  ],
  "backtest_window": [
    "2025-08-05 13:00:00",
    "2025-08-12 13:00:00"
  ],
  "model_path": "checkpoints/best_model_episode_250.pt",
  "oos": {
    "win_rate": 0.0,
    "composite_score": 0.025443786982248518,
    "trades_per_day": 0.14201183431952663
  },
  "backtest": {
    "win_rate": 0.25,
    "composite_score": 0.0,
    "trades_per_day": 0.6620689655172414
  },
  "timestamp": "2025-08-14T04:04:33.800508"
}